MANIFEST.in
README.md
requirements.txt
setup.cfg
setup.py
versioneer.py
botcity/plugins/captcha/__init__.py
botcity/plugins/captcha/_version.py
botcity/plugins/captcha/plugin.py
botcity_captcha_plugin.egg-info/PKG-INFO
botcity_captcha_plugin.egg-info/SOURCES.txt
botcity_captcha_plugin.egg-info/dependency_links.txt
botcity_captcha_plugin.egg-info/requires.txt
botcity_captcha_plugin.egg-info/top_level.txt
tests/test_import.py
tests/test_plugin.py