Metadata-Version: 2.1
Name: botcity-captcha-plugin
Version: 0.1.6
Home-page: https://bitbucket.org/botcitydev/bot-captcha-plugin-python.git
Requires-Python: >=3.7
